assesspy/__init__.py
assesspy/ci.py
assesspy/load_data.py
assesspy/metrics.py
assesspy/outliers.py
assesspy/sales_chasing.py
assesspy/utils.py
assesspy/data/__init__.py
assesspy/data/ccao_sample.parquet
assesspy/tests/__init__.py
assesspy/tests/conftest.py
assesspy/tests/test_ci.py
assesspy/tests/test_metrics.py
assesspy/tests/test_outliers.py
assesspy/tests/test_sales_chasing.py
assesspy-2.0.2.dist-info/LICENSE
assesspy-2.0.2.dist-info/METADATA
assesspy-2.0.2.dist-info/WHEEL
assesspy-2.0.2.dist-info/top_level.txt
assesspy-2.0.2.dist-info/RECORD
