Metadata-Version: 2.2
Name: assesspy
Version: 2.0.2
Summary: Python package for measuring assessment performance
Author-email: William Ridgeway <william.ridgeway@cookcountyil.gov>, Dan Snow <daniel.snow@cookcountyil.gov>, Michael Wagner <michael.wagner2@cookcountyil.gov>
License:                     GNU AFFERO GENERAL PUBLIC LICENSE
Project-URL: Repository, https://github.com/ccao-data/assesspy
Project-URL: Documentation, https://ccao-data.github.io/assesspy/
Keywords: assessment,property taxes,local government
Classifier: Development Status :: 4 - Beta
Classifier: Intended Audience :: Developers
Classifier: License :: OSI Approved :: GNU Affero General Public License v3
Classifier: Programming Language :: Python :: 3.9
Classifier: Programming Language :: Python :: 3.10
Classifier: Programming Language :: Python :: 3.11
Classifier: Programming Language :: Python :: 3.12
Classifier: Programming Language :: Python :: 3.13
Requires-Python: >=3.9
License-File: LICENSE
Requires-Dist: numpy>=1.23.1
Requires-Dist: pandas>=1.4.3
Requires-Dist: pyarrow>=9.0.0
Requires-Dist: statsmodels>=0.13.2
Provides-Extra: dev
Requires-Dist: setuptools>=61.0; extra == "dev"
Requires-Dist: pytest>=7.0.0; extra == "dev"
Requires-Dist: pytest-cov>=4.0.0; extra == "dev"
Provides-Extra: docs
Requires-Dist: setuptools; extra == "docs"
Requires-Dist: myst-nb; extra == "docs"
Requires-Dist: sphinx; extra == "docs"
Requires-Dist: sphinx-pyproject; extra == "docs"
Requires-Dist: pydata-sphinx-theme; extra == "docs"
Requires-Dist: ipykernel; extra == "docs"
Requires-Dist: matplotlib; extra == "docs"
